Jenkinsfile
MANIFEST.in
README.rst
setup.py
svn-ignore
buildouts/plone4/buildout.cfg
buildouts/plone4/install.sh
buildouts/plone4/versions.cfg
docs/HISTORY.txt
docs/LICENSE.GPL
docs/LICENSE.txt
eea/__init__.py
eea.google.egg-info/PKG-INFO
eea.google.egg-info/SOURCES.txt
eea.google.egg-info/dependency_links.txt
eea.google.egg-info/entry_points.txt
eea.google.egg-info/namespace_packages.txt
eea.google.egg-info/not-zip-safe
eea.google.egg-info/requires.txt
eea.google.egg-info/top_level.txt
eea/google/README.txt
eea/google/__init__.py
eea/google/configure.zcml
eea/google/profiles.zcml
eea/google/skins.zcml
eea/google/version.txt
eea/google/analytics/__init__.py
eea/google/analytics/analytics.css
eea/google/analytics/analytics.gif
eea/google/analytics/analytics.pt
eea/google/analytics/browser.py
eea/google/analytics/configure.zcml
eea/google/analytics/connection.py
eea/google/analytics/content.py
eea/google/analytics/editpageform.pt
eea/google/analytics/interfaces.py
eea/google/analytics/namechooser.py
eea/google/analytics/report.gif
eea/google/analytics/report.pt
eea/google/analytics/vocabularies.py
eea/google/analytics/vocabularies.zcml
eea/google/analytics/xmlparser.py
eea/google/api/__init__.py
eea/google/api/connection.py
eea/google/api/exception.py
eea/google/docs/analytics.txt
eea/google/docs/api.txt
eea/google/docs/tool.txt
eea/google/profiles/default/componentregistry.xml
eea/google/profiles/default/controlpanel.xml
eea/google/profiles/default/cssregistry.xml
eea/google/profiles/default/metadata.xml
eea/google/profiles/default/skins.xml
eea/google/profiles/default/toolset.xml
eea/google/skins/eea_google/portlet_analytics.pt
eea/google/tests/__init__.py
eea/google/tests/base.py
eea/google/tests/test_doctests.py
eea/google/tests/data/analytics.xml
eea/google/tool/__init__.py
eea/google/tool/browser.py
eea/google/tool/configure.zcml
eea/google/tool/google.py
eea/google/tool/icon.gif
eea/google/tool/interfaces.py
eea/google/tool/view.pt
eea/google/upgrades/__init__.py
eea/google/upgrades/configure.zcml